PyInvestor/__init__.py
PyInvestor/market.py
PyInvestor/stock.py
PyInvestor/test_market.py
PyInvestor/test_stock.py
PyInvestor/utils.py
pyinvestor-0.0.2.dist-info/LICENSE
pyinvestor-0.0.2.dist-info/METADATA
pyinvestor-0.0.2.dist-info/WHEEL
pyinvestor-0.0.2.dist-info/top_level.txt
pyinvestor-0.0.2.dist-info/RECORD
