Metadata-Version: 2.1
Name: pyinvestor
Version: 0.0.2
Summary: python wrapper for the IEX API
Home-page: https://github.com/SamurAi-sarl/PyInvestor
Author: SamurAI Sarl (Fabio Capela)
Author-email: fabio.capela@samurai.team
License: Apache-2.0
Keywords: finance,trading,stock,IEX,API,market
Platform: UNKNOWN
Requires-Dist: pandas
Requires-Dist: requests
